EasyPandas/__init__.py
EasyPandas/apply.py
EasyPandas/cut.py
EasyPandas/dummy.py
EasyPandas/duplicate.py
EasyPandas/factor.py
EasyPandas/filter.py
EasyPandas/freq.py
EasyPandas/freq2d.py
EasyPandas/group.py
EasyPandas/index.py
EasyPandas/merge.py
EasyPandas/na.py
EasyPandas/numdesc.py
EasyPandas/pivot.py
EasyPandas/plot.py
EasyPandas/read.py
EasyPandas/reshape.py
EasyPandas/sort.py
EasyPandas/stack.py
EasyPandas/strdesc.py
EasyPandas/totime.py
EasyPandas/write.py
easypandas-0.0.3.dist-info/METADATA
easypandas-0.0.3.dist-info/WHEEL
easypandas-0.0.3.dist-info/licenses/LICENSE
easypandas-0.0.3.dist-info/RECORD
