Metadata-Version: 2.1
Name: EasyPandas
Version: 0.0.3
Summary: 使用Pandas库处理数据的简洁程序库
Project-URL: Homepage, https://github.com/LiuAndy-art/EasyPandas
Project-URL: Documentation, https://github.com/LiuAndy-art/EasyPandas
Project-URL: Repository, https://github.com/LiuAndy-art/EasyPandas
Author-email: LiuAndy <andylau_dh@163.com>
Maintainer-email: LiuAndy <andylau_dh@163.com>
License: MIT License
License-File: LICENSE
Keywords: Pandas,函数封装,数据分析,简介代码
Classifier: License :: OSI Approved :: MIT License
Classifier: Operating System :: OS Independent
Classifier: Programming Language :: Python :: 3
Requires-Python: >=3.8
Requires-Dist: matplotlib
Requires-Dist: numpy
Requires-Dist: openpyxl
Requires-Dist: pandas
Requires-Dist: pyreadstat
Requires-Dist: xlrd
Requires-Dist: xlsxwriter
Requires-Dist: xlwt
